[
    {
        "created": "20211226155856632",
        "creator": "林一二",
        "text": "",
        "title": "gt6796c/mermaid-tw5",
        "modified": "20211226160331066",
        "modifier": "林一二",
        "tags": "$:/tags/PluginWiki",
        "type": "text/vnd.tiddlywiki",
        "uri": "https://efurlanm.github.io/mermaid-tw5.html",
        "_title": "gt6796c/mermaid-tw5",
        "_type": "plugin",
        "author": "gt6796c",
        "description": "Mermaid lets you create diagrams and visualizations using text and code.",
        "name": "mermaid-tw5",
        "readme": "This is a TiddlyWiki plugin for using [[mermaid.js|https://mermaid-js.github.io/mermaid/#/]].\n\nIt is completely self-contained, and doesn't need an Internet connection in order to work. It works both in the browser and under Node.js.\n\nIt is currently based on [[mermaid.js 8.13.2|http://mermaid-js.github.io/mermaid]]\n\n!! Installation\nYou can drag the plugin link into your TiddlyWiki to install, from http://efurlanm.github.io/mermaid-tw5\n\n!! Dependencies\n;This plugin requires:\n*[[rocklib Plugin|https://gt6796c.github.io]]\n(will be auto installed by CPL)",
        "sourse": "https://github.com/efurlanm/mermaid-tw5",
        "plugin-icon": "https://mermaid-js.github.io/mermaid/img/header.png",
        "documentation": "https://efurlanm.github.io/mermaid-tw5",
        "dependents": "gt6796c/rocklib"
    }
]