[
    {
        "tags": "$:/tags/PluginWiki",
        "cpl.readme": "; Manage Tags\n: Add or Delete tags in view mode\n\n!! Settings\n\n<div style=\"margin-left: 25px;\">\n\n<$checkbox tiddler=\"$:/xp/ui/Buttons/manage-tags\" tag=\"$:/tags/ViewToolbar\">\n [[Show in View Toolbar|$:/xp/ui/Buttons/manage-tags]]\n</$checkbox><br>\n<$checkbox tiddler=\"$:/xp/ui/Buttons/manage-tags\" tag=\"$:/tags/PageControls\">\n [[Show in Page Toolbar|$:/xp/ui/Buttons/manage-tags]]\n</$checkbox>\n\n</div>",
        "cpl.uri": "https://keatonlao.github.io/tiddlywiki-xp/index.html",
        "cpl.title": "$:/plugins/xp/managetags",
        "cpl.author": "TonGerner",
        "cpl.name": "Manage Tags",
        "cpl.description": "Add or Delete tags in view mode",
        "cpl.plugin-type": "plugin",
        "cpl.source": "http://tw5custom.tiddlyspot.com",
        "cpl.dependents": "",
        "title": "Plugin_202207204818746"
    }
]