{"title":"$:/plugins/venomspinner/ghostwriter","author":"Venomspinner","name":"Ghostwriter","description":"A minimalist, mobile responsive theme for blogging","readme":"<$button class=\"tc-btn-invisible\" style=\"overflow: hidden;white-space: pre;width: 100%;\" message=\"tm-open-external-window\" param=\"https://ibnishak.github.io/irreverent-mudblood/\">{{$:/core/images/github}} <$text text=\"https://ibnishak.github.io/irreverent-mudblood/\"/></$button>\n\n","version":"1.0.9","plugin-type":"theme","dependents":"$:/themes/tiddlywiki/vanilla","requires-reload":false,"category":"Unknown","type":"application/json","latest":"1.0.9","versions":{}}