{"title":"$:/plugins/kookma/pikaday","author":"Nicolas Petton, Mohammad Rahmani","name":"Pikaday","description":"Date picker from Projectify","readme":"<$button class=\"tc-btn-invisible\" style=\"overflow: hidden;white-space: pre;width: 100%;\" message=\"tm-open-external-window\" param=\"https://github.com/kookma/TW-Pikaday\">{{$:/core/images/github}} <$text text=\"https://github.com/kookma/TW-Pikaday\"/></$button>\n\n; Pikaday\nA date-picker with calendar widget to pick a date and set to `due` field of target tiddler. This is a derived plugin from Projectify by [[Nicolas Petton|https://nicolas.petton.fr]] nicolas@petton.fr\n\n;Code and demo\nFor learning plugin features, syntax, tutorial and examples see the plugin demo and code pages\n\n* Demo: https://kookma.github.io/TW-Pikaday/\n* Code: https://github.com/kookma/TW-Pikaday\n","version":"0.7.0","plugin-type":"plugin","core-version":">=5.2.3","requires-reload":false,"category":"Unknown","type":"application/json","latest":"0.7.0","versions":["0.6.0","0.7.0"],"versions-size":{"0.6.0":74697,"0.7.0":74735}}