{"title":"$:/plugins/linonetwo/source-control-management","author":"LinOnetwo","name":"SCM","description":"Use TiddlyGit's NodeJS API to sync data to git on the cloud","readme":"<$button class=\"tc-btn-invisible\" style=\"overflow: hidden;white-space: pre;width: 100%;\" message=\"tm-open-external-window\" param=\"https://github.com/tiddly-gittly/tiddlywiki-plugins/tree/master/plugins/linonetwo/source-control-management\">{{$:/core/images/github}} <$text text=\"https://github.com/tiddly-gittly/tiddlywiki-plugins/tree/master/plugins/linonetwo/source-control-management\"/></$button>\n\n!! 功能\n\n[[WebCatalog|https://webcatalogapp.com/]] 除了[[能将 TiddlyWiki 包装成桌面应用|https://onetwo.ren/%E7%94%A8tiddlywiki%E6%9B%BF%E4%BB%A3notion%E5%92%8Cevernote%E7%AE%A1%E7%90%86%E7%9F%A5%E8%AF%86/]]以外，还提供了自定义 API 并暴露给网页的功能，让我们可以在 Wiki 网页里使用一些高级功能。\n\n本插件利用暴露的自定义 API 实现：\n\n# 查看本地 NodeJS 版 TiddlyWiki 是否完全与 Github 备份云同步了\n# 一键同步本地和云端\n\n!! 用法\n\n当点开 SCM 标签页的时候，会进行一次 git 环境检查，因为使用的 git 库 dugite 比较卡，所以只进行一次检查，如果需要刷新，需要来回切换一下 tab。\n","version":"0.1.4","plugin-type":"plugin","core-version":">=5.1.22","requires-reload":false,"category":"Unknown","type":"application/json","latest":"0.1.4","versions":["0.1.4"],"versions-size":{"0.1.4":19591}}